.bumpversion.cfg
.coveragerc
.editorconfig
.pre-commit-config.yaml
.readthedocs.yml
AUTHORS.rst
CHANGELOG.rst
CONTRIBUTING.rst
LICENSE
MANIFEST.in
README.rst
pyproject.toml
setup.cfg
setup.py
tox.ini
ci/bootstrap.py
ci/requirements.txt
docs/authors.rst
docs/changelog.rst
docs/conf.py
docs/contributing.rst
docs/index.rst
docs/installation.rst
docs/readme.rst
docs/requirements.txt
docs/spelling_wordlist.txt
docs/usage.rst
docs/reference/index.rst
docs/reference/scheckcli.rst
src/scheckcli/__init__.py
src/scheckcli/__main__.py
src/scheckcli/cli.py
src/scheckcli.egg-info/PKG-INFO
src/scheckcli.egg-info/SOURCES.txt
src/scheckcli.egg-info/dependency_links.txt
src/scheckcli.egg-info/entry_points.txt
src/scheckcli.egg-info/not-zip-safe
src/scheckcli.egg-info/requires.txt
src/scheckcli.egg-info/top_level.txt
tests/test_scheckcli.py