Metadata-Version: 2.1
Name: scheckcli
Version: 1.0.4
Summary: A cli tool to perform json and yaml object schema validation.
Home-page: https://gitlab.com/ronmallory/python-scheckcli
Author: Ron Mallory
Author-email: ronnymallory@gmail.com
License: MIT
Project-URL: Documentation, https://python-scheckcli.readthedocs.io/
Project-URL: Changelog, https://python-scheckcli.readthedocs.io/en/latest/changelog.html
Project-URL: Issue Tracker, https://gitlab.com/ronmallory/python-scheckcli/issues
Platform: UNKNOWN
Classifier: Development Status :: 5 - Production/Stable
Classifier: Intended Audience :: Developers
Classifier: License :: OSI Approved :: MIT License
Classifier: Operating System :: Unix
Classifier: Operating System :: POSIX
Classifier: Operating System :: Microsoft :: Windows
Classifier: Programming Language :: Python
Classifier: Programming Language :: Python :: 3
Classifier: Programming Language :: Python :: 3 :: Only
Classifier: Programming Language :: Python :: 3.6
Classifier: Programming Language :: Python :: 3.7
Classifier: Programming Language :: Python :: 3.8
Classifier: Programming Language :: Python :: 3.9
Classifier: Programming Language :: Python :: 3.10
Classifier: Programming Language :: Python :: Implementation :: CPython
Classifier: Programming Language :: Python :: Implementation :: PyPy
Classifier: Topic :: Utilities
Requires-Python: >=3.6
License-File: LICENSE
License-File: AUTHORS.rst
